tee_cli/__main__.py
tee_cli-0.2.0.dist-info/LICENSE
tee_cli-0.2.0.dist-info/METADATA
tee_cli-0.2.0.dist-info/WHEEL
tee_cli-0.2.0.dist-info/entry_points.txt
tee_cli-0.2.0.dist-info/RECORD
